sdelmo/__init__.py
sdelmo/sdelmo.py
sdelmo-2.0.2.dist-info/LICENSE
sdelmo-2.0.2.dist-info/METADATA
sdelmo-2.0.2.dist-info/WHEEL
sdelmo-2.0.2.dist-info/top_level.txt
sdelmo-2.0.2.dist-info/RECORD
