Metadata-Version: 2.1
Name: sdelmo
Version: 2.0.2
Summary: Simple downloader for soundcloud
Home-page: https://github.com/elmoiv/sdelmo
Author: elmoiv
Author-email: elmoiv@yahoo.com
License: UNKNOWN
Platform: UNKNOWN
Classifier: Programming Language :: Python :: 3
Classifier: License :: OSI Approved :: MIT License
Classifier: Operating System :: OS Independent
Requires-Python: >=3.4
Requires-Dist: requests
Requires-Dist: lxml
